{
  "assets": [
    {
      "id": "phone-system",
      "name": "Advanced Phone System V3 Replicated",
      "description": "Complete multiplayer phone system with messaging, calls, contacts, and more. Fully replicated for multiplayer games. Features include SMS messaging, call functionality, contact management, notification system, and customizable UI. Perfect for GTA-style games or any project requiring in-game communication.",
      "price": 50,
      "currency": "USD",
      "link": "https://www.fab.com/listings/e627507f-3dbd-4b88-8e3e-db4dc1730fdd",
      "tags": [
        "Multiplayer",
        "UI System",
        "Blueprint"
      ],
      "featured": true,
      "images": [
        "../DataList/Phone/c8a11308-048c-416a-b73b-2a42dd3331a8.jpg",
        "../DataList/Phone/0bbe84ab-75a0-4ed8-b0f9-36e4c1e32bce.jpg",
        "../DataList/Phone/601477a1-1579-472a-a46d-b09f929ac68d.jpg",
        "../DataList/Phone/847f52af-a04d-4527-b01b-3be7e54be67b.jpg"
      ]
    },
    {
      "id": "market-system",
      "name": "Advanced Market System",
      "description": "Full-featured marketplace system with inventory, trading, and economy management. Perfect for RPGs and MMOs. Includes buy/sell functionality, dynamic pricing, inventory management, item categories, search and filter options, and fully networked for multiplayer games.",
      "price": 50,
      "currency": "USD",
      "link": "https://www.fab.com/listings/4a319804-03da-4d35-9d73-85d5871dd2ea",
      "tags": [
        "Economy",
        "Inventory",
        "Multiplayer"
      ],
      "featured": true,
      "images": [
        "../DataList/Market/3addfac8-6c36-4e59-8a7f-f3b68d274286.jpg",
        "../DataList/Market/2d6d11c9-ff57-4b16-a06f-4ccd089c0f87.jpg",
        "../DataList/Market/2d924be4-960f-4b36-a32a-69e16bb53a59.jpg",
        "../DataList/Market/a2d0e70a-7b1a-4ab8-ad8a-3eaa29463e12.jpg"
      ]
    },
    {
      "id": "dialogue-system",
      "name": "NBDS - Node Based Dialogue System",
      "description": "Powerful node-based dialogue editor with multiplayer support. Create complex branching conversations easily. Features include visual node editor, conditional branching, variable system, localization support, and seamless multiplayer integration. Great for RPGs, adventure games, and interactive narratives.",
      "price": 30,
      "currency": "USD",
      "link": "https://www.fab.com/listings/204eb999-fa5d-4675-9b37-c1f628d79f2b",
      "tags": [
        "Dialogue",
        "Node Editor",
        "Multiplayer"
      ],
      "featured": false,
      "images": [
        "../DataList/Dialogue/132c3891-429f-49c1-9f9b-806030c82f5a.jpg",
        "../DataList/Dialogue/05c8001f-5ecd-4a2a-8206-fab224ad5085.jpg",
        "../DataList/Dialogue/43f4027a-44aa-4256-9e13-63a7f06c2224.jpg",
        "../DataList/Dialogue/471cd2e2-070c-4773-8576-a2880cd4f2a3.jpg"
      ]
    },
    {
      "id": "flying-carpet",
      "name": "Multiplayer Flying Carpet/Broom",
      "description": "Magical flying system with Follow AI. Perfect for fantasy games with Harry Potter-style flying mechanics. Includes smooth flight controls, multiplayer replication, AI companion that follows the player, customizable speed and handling, and beautiful visual effects.",
      "price": 30,
      "currency": "USD",
      "link": "https://www.fab.com/listings/7b171ff8-616a-4a10-9768-8400fbe93aea",
      "tags": [
        "Movement",
        "AI",
        "Multiplayer"
      ],
      "featured": false,
      "images": [
        "../DataList/flying_Carpet/d35cad64-f06b-413e-ae1a-6b37db795a99.jpg",
        "../DataList/flying_Carpet/133bea81-c4a2-48bd-821d-3db1cad1563b.jpg",
        "../DataList/flying_Carpet/6fa8d53d-a217-4464-a90f-e86fe4c20030.jpg",
        "../DataList/flying_Carpet/b26fe9f0-1f79-4dac-a23a-adb07a7eed04.jpg"
      ]
    },
    {
      "id": "rc-car",
      "name": "RC Car System V1",
      "description": "Remote controlled car system with realistic physics. Great for mini-games and vehicle mechanics. Features include realistic RC car physics, camera switching, range limitations, battery system, and customizable car properties.",
      "price": 10,
      "currency": "USD",
      "link": "https://www.fab.com/listings/8dce82ac-ed9d-471f-9f8e-5fbe89e81b2d",
      "tags": [
        "Vehicle",
        "Physics",
        "Gameplay"
      ],
      "featured": false,
      "images": [
        "../DataList/carsystem.jpg"
      ]
    },
    {
      "id": "combination-lock",
      "name": "Multiplayer Combination Lock",
      "description": "Interactive combination lock system with multiplayer sync. Perfect for escape rooms and puzzle games. Includes customizable digit count, visual and audio feedback, replicated state for multiplayer, easy integration, and Blueprint-friendly API.",
      "price": 10,
      "currency": "USD",
      "link": "https://www.fab.com/listings/9f9a7d3d-b913-480d-ad1d-e875e12ee836",
      "tags": [
        "Puzzle",
        "Interactive",
        "Multiplayer"
      ],
      "featured": false,
      "images": [
        "../DataList/lock/1219cec9-5683-43fb-9695-251cfa09b352.jpg",
        "../DataList/lock/023bff4c-257e-42f4-8bc5-2e46eb805e65.jpg",
        "../DataList/lock/dae56253-1a6c-493f-ad02-93266fb29ed2.jpg"
      ]
    },
    {
      "id": "video-chat",
      "name": "Multiplayer Video Chat",
      "description": "In-game video chat system for multiplayer games. Enable players to communicate face-to-face. Features webcam integration, picture-in-picture display, mute controls, and seamless network replication.",
      "price": 7,
      "currency": "USD",
      "link": "https://www.fab.com/listings/a07aa037-ba61-4b02-81b4-028a21232281",
      "tags": [
        "Communication",
        "Video",
        "Multiplayer"
      ],
      "featured": false,
      "images": [
        "../DataList/videochat.jpg"
      ]
    },
    {
      "id": "editor-save",
      "name": "Editor Save System",
      "description": "Save and load system for Unreal Editor. Preserve your work and settings effortlessly. Quick save/load functionality, multiple save slots, and seamless integration with Unreal Editor workflow.",
      "price": 3,
      "currency": "USD",
      "link": "https://www.fab.com/listings/1f370f2b-2bd7-4aa7-a9fb-343be515371e",
      "tags": [
        "Editor",
        "Utility",
        "Save/Load"
      ],
      "featured": false,
      "images": [
        "../DataList/editorsave.jpg"
      ]
    }
  ],
  "siteInfo": {
    "storeName": "SametStore",
    "tagline": "Premium Unreal Engine Assets",
    "fabStoreUrl": "https://www.fab.com/sellers/SametStore",
    "aboutText": "SametStore is a dedicated Unreal Engine asset developer focused on creating high-quality, production-ready multiplayer systems and game mechanics. With a passion for game development and years of experience in Unreal Engine, we deliver assets that are not just functional, but also well-optimized and thoroughly documented.",
    "aboutText2": "Every asset we create is built with multiplayer in mind, ensuring seamless replication and synchronization across all clients. We believe in providing value to indie developers and studios alike, helping them accelerate their game development process."
  }
}